wagtail_managed404/__init__.py
wagtail_managed404/apps.py
wagtail_managed404/middleware.py
wagtail_managed404/models.py
wagtail_managed404/wagtail_hooks.py
wagtail_managed404/migrations/0001_initial.py
wagtail_managed404/migrations/__init__.py
wagtail_managed404-0.1.1.dist-info/METADATA
wagtail_managed404-0.1.1.dist-info/RECORD
wagtail_managed404-0.1.1.dist-info/WHEEL
wagtail_managed404-0.1.1.dist-info/top_level.txt
