Metadata-Version: 2.1
Name: wagtail-managed404
Version: 0.1.1
Summary: Easily manage 404s from the wagtail admin
Home-page: https://github.com/mwesterhof/wagtail_managed404
Author: Marco Westerhof
Author-email: m.westerhof@lukkien.com
License: MIT license
Keywords: wagtail_managed404
Platform: UNKNOWN
Classifier: Development Status :: 2 - Pre-Alpha
Classifier: Intended Audience :: Developers
Classifier: License :: OSI Approved :: MIT License
Classifier: Natural Language :: English
Classifier: Programming Language :: Python :: 3
Classifier: Programming Language :: Python :: 3.6
Classifier: Programming Language :: Python :: 3.7
Requires-Dist: wagtailfontawesome
